elf_diff/__init__.py
elf_diff/__main__.py
elf_diff/auxiliary.py
elf_diff/binary.py
elf_diff/binary_file_format.py
elf_diff/binary_pair.py
elf_diff/binary_pair_settings.py
elf_diff/binutils.py
elf_diff/default_plugins.py
elf_diff/document_explorer.py
elf_diff/error_handling.py
elf_diff/formatted_output.py
elf_diff/git.py
elf_diff/instruction_collector.py
elf_diff/jinja.py
elf_diff/mangling.py
elf_diff/meta_tree.py
elf_diff/meta_tree_properties.py
elf_diff/pair_report_document.py
elf_diff/plugin.py
elf_diff/settings.py
elf_diff/source_file.py
elf_diff/string_diff.py
elf_diff/symbol.py
elf_diff/symbol_extractor.py
elf_diff/symbol_selection.py
elf_diff/symbol_sizes.py
elf_diff/system_command.py
elf_diff/tree_addressable.py
elf_diff/tree_exception.py
elf_diff/value_tree.py
elf_diff/deprecated/__init__.py
elf_diff/deprecated/mass_report.py
elf_diff/deprecated/j2/mass_report_template.html
elf_diff/deprecated/j2/css/elf_diff_general.css
elf_diff/deprecated/j2/css/layout.css
elf_diff/deprecated/j2/js/sorttable.js
elf_diff/html/example_page.html
elf_diff/images/elf_diff_logo.svg
elf_diff/images/elf_diff_logo_favicon.svg
elf_diff/images/favicon.png
elf_diff/plugins/__init__.py
elf_diff/plugins/export/__init__.py
elf_diff/plugins/export/html/__init__.py
elf_diff/plugins/export/html/plugin.py
elf_diff/plugins/export/html/j2/document.html
elf_diff/plugins/export/html/j2/frame_content.html
elf_diff/plugins/export/html/j2/isolated_symbol_details.html
elf_diff/plugins/export/html/j2/isolated_symbol_overview.html
elf_diff/plugins/export/html/j2/macros.j2
elf_diff/plugins/export/html/j2/migrated_symbol_details.html
elf_diff/plugins/export/html/j2/migrated_symbol_overview.html
elf_diff/plugins/export/html/j2/pair_report_index_page.html
elf_diff/plugins/export/html/j2/pair_report_single_page.html
elf_diff/plugins/export/html/j2/persisting_symbol_details.html
elf_diff/plugins/export/html/j2/persisting_symbol_overview.html
elf_diff/plugins/export/html/j2/similar_symbol_details.html
elf_diff-0.7.1.dist-info/LICENSE.txt
elf_diff-0.7.1.dist-info/METADATA
elf_diff-0.7.1.dist-info/WHEEL
elf_diff-0.7.1.dist-info/top_level.txt
elf_diff-0.7.1.dist-info/RECORD
