Metadata-Version: 2.1
Name: elf_diff
Version: 0.7.1
Summary: A tool to compare elf binaries
Home-page: https://github.com/noseglasses/elf_diff
Author: noseglasses
Author-email: shinynoseglasses@gmail.com
License: GPL 3
Classifier: Development Status :: 4 - Beta
Classifier: Environment :: Console
Classifier: Intended Audience :: Developers
Classifier: Intended Audience :: Education
Classifier: License :: OSI Approved :: GNU General Public License v3 (GPLv3)
Classifier: Natural Language :: English
Classifier: Operating System :: OS Independent
Classifier: Programming Language :: Python :: 3.6
Classifier: Programming Language :: Python :: 3.7
Classifier: Programming Language :: Python :: 3.8
Classifier: Programming Language :: Python :: 3.9
Classifier: Programming Language :: Python :: 3.10
Classifier: Topic :: Software Development :: Bug Tracking
Classifier: Topic :: Software Development :: Quality Assurance
Classifier: Topic :: Utilities
Classifier: Topic :: Education
Requires-Python: >=3.6
License-File: LICENSE.txt
Requires-Dist: setuptools-git
Requires-Dist: jinja2
Requires-Dist: pyyaml
Requires-Dist: progressbar2
Requires-Dist: GitPython
Requires-Dist: weasyprint
Requires-Dist: anytree
Requires-Dist: dict2xml
